locust/__init__.py
locust/__main__.py
locust/argument_parser.py
locust/clients.py
locust/debug.py
locust/dispatch.py
locust/env.py
locust/event.py
locust/exception.py
locust/html.py
locust/input_events.py
locust/log.py
locust/main.py
locust/py.typed
locust/runners.py
locust/shape.py
locust/stats.py
locust/web.py
locust/contrib/__init__.py
locust/contrib/fasthttp.py
locust/rpc/__init__.py
locust/rpc/protocol.py
locust/rpc/zmqrpc.py
locust/static/chart.js
locust/static/echarts.common.min.js
locust/static/jquery-1.11.3.min.js
locust/static/jquery.jqote2.min.js
locust/static/jquery.tools.min.js
locust/static/locust.js
locust/static/tasks.js
locust/static/vintage.js
locust/static/css/application.css
locust/static/css/application.css.map
locust/static/css/tables.css
locust/static/css/tables.css.map
locust/static/img/favicon.ico
locust/static/img/logo.png
locust/static/img/ui-screenshot-charts.png
locust/static/img/ui-screenshot-start-test.png
locust/static/img/ui-screenshot-stats.png
locust/static/img/ui-screenshot-workers.png
locust/static/sass/_base.sass
locust/static/sass/_mixins.sass
locust/static/sass/application.sass
locust/static/sass/tables.sass
locust/templates/index.html
locust/templates/report.html
locust/templates/stats_data.html
locust/test/__init__.py
locust/test/fake_module1_for_env_test.py
locust/test/fake_module2_for_env_test.py
locust/test/mock_locustfile.py
locust/test/mock_logging.py
locust/test/test_dispatch.py
locust/test/test_env.py
locust/test/test_fasthttp.py
locust/test/test_http.py
locust/test/test_load_locustfile.py
locust/test/test_locust_class.py
locust/test/test_log.py
locust/test/test_main.py
locust/test/test_old_wait_api.py
locust/test/test_parser.py
locust/test/test_runners.py
locust/test/test_sequential_taskset.py
locust/test/test_stats.py
locust/test/test_tags.py
locust/test/test_taskratio.py
locust/test/test_users.py
locust/test/test_util.py
locust/test/test_wait_time.py
locust/test/test_web.py
locust/test/test_zmqrpc.py
locust_je_test_pep621-0.0.0.dist-info/LICENSE
locust_je_test_pep621-0.0.0.dist-info/METADATA
locust_je_test_pep621-0.0.0.dist-info/WHEEL
locust_je_test_pep621-0.0.0.dist-info/entry_points.txt
locust_je_test_pep621-0.0.0.dist-info/top_level.txt
locust_je_test_pep621-0.0.0.dist-info/RECORD
