Metadata-Version: 2.1
Name: locust-je-test-pep621
Version: 0.0.0
Summary: Developer friendly load testing framework
Home-page: https://locust.io/
License: The MIT License
Project-URL: Homepage, https://locust.io/
Project-URL: Documentation, https://docs.locust.io/
Project-URL: Code, https://github.com/locustio/locust
Project-URL: Help/Questions, https://stackoverflow.com/questions/tagged/locust
Project-URL: Issue tracker, https://github.com/locustio/locust/issues
Classifier: Topic :: Software Development :: Testing :: Traffic Generation
Classifier: Development Status :: 5 - Production/Stable
Classifier: License :: OSI Approved :: MIT License
Classifier: Operating System :: OS Independent
Classifier: Programming Language :: Python
Classifier: Programming Language :: Python :: 3
Classifier: Programming Language :: Python :: 3.7
Classifier: Programming Language :: Python :: 3.8
Classifier: Programming Language :: Python :: 3.9
Classifier: Programming Language :: Python :: 3.10
Classifier: Programming Language :: Python :: 3.11
Classifier: Intended Audience :: Developers
Classifier: Intended Audience :: System Administrators
Classifier: Topic :: Software Development :: Testing
Classifier: Topic :: Software Development :: Testing :: Traffic Generation
Classifier: Topic :: System :: Distributed Computing
Requires-Python: >=3.7
License-File: LICENSE
Requires-Dist: gevent (>=20.12.1)
Requires-Dist: flask (>=2.0.0)
Requires-Dist: Werkzeug (>=2.0.0)
Requires-Dist: requests (>=2.23.0)
Requires-Dist: msgpack (>=0.6.2)
Requires-Dist: pyzmq (!=23.0.0,>=22.2.1)
Requires-Dist: geventhttpclient (>=2.0.2)
Requires-Dist: ConfigArgParse (>=1.0)
Requires-Dist: psutil (>=5.6.7)
Requires-Dist: Flask-BasicAuth (>=0.2.0)
Requires-Dist: Flask-Cors (>=3.0.10)
Requires-Dist: roundrobin (>=0.0.2)
Requires-Dist: typing-extensions (>=3.7.4.3)
Requires-Dist: pywin32 ; platform_system == "Windows"
